aceto/__init__.py
aceto/band_system.py
aceto/lab_settings.py
aceto/nr3td.py
aceto/nr3td_fic.cpython-35m-darwin.so
aceto/scripts/__init__.py
aceto/scripts/aceto_conf.py
aceto-0.0.5.dist-info/DESCRIPTION.rst
aceto-0.0.5.dist-info/METADATA
aceto-0.0.5.dist-info/RECORD
aceto-0.0.5.dist-info/WHEEL
aceto-0.0.5.dist-info/entry_points.txt
aceto-0.0.5.dist-info/metadata.json
aceto-0.0.5.dist-info/top_level.txt
lib/libaceto.a
tests/bdd/__init__.py
tests/unit/__init__.py
