Metadata-Version: 2.0
Name: aceto
Version: 0.0.5
Summary: Accelerated Charge and Energy Transfer Objects
Home-page: https://github.com/tmancal74/aceto
Author: Tomas Mancal
Author-email: mancal@karlov.mff.cuni.cz
License: MIT
Keywords: physics,chemistry,quantum mechanics,open quantum systems
Platform: UNKNOWN
Classifier: Development Status :: 3 - Alpha
Classifier: Intended Audience :: Science/Research
Classifier: Intended Audience :: Education
Classifier: Topic :: Scientific/Engineering :: Physics
Classifier: Topic :: Scientific/Engineering :: Chemistry
Classifier: License :: OSI Approved :: MIT License
Classifier: Programming Language :: Python :: 3
Classifier: Programming Language :: Python :: 3.3
Classifier: Programming Language :: Python :: 3.4
Classifier: Programming Language :: Python :: 3.5
